tacomail/__init__.py
tacomail/cli.py
tacomail/tacomail.py
tacomail-0.3.0.dist-info/METADATA
tacomail-0.3.0.dist-info/WHEEL
tacomail-0.3.0.dist-info/entry_points.txt
tacomail-0.3.0.dist-info/RECORD
