Metadata-Version: 2.4
Name: tacomail
Version: 0.3.0
Summary: A Python client for Tacomail
Author-email: sokripon <sokripon@gmail.com>
Requires-Python: >=3.12
Requires-Dist: httpx>=0.28.0
Requires-Dist: rich>=13.0.0
Requires-Dist: typer>=0.12.0
